{
  "simulation_index": 78379,
  "signature_hash": "a5e1182784ac32005a329fcfc10de3343eda92a1",
  "log_probability": -54.88644415434211,
  "log10_probability": -23.83687982752177,
  "first_four": [
    {
      "round": "FirstFour",
      "round_label": "First Four",
      "region": "Midwest",
      "slot_label": "Midwest 11 play-in",
      "winner_id": "mia_oh",
      "winner_name": "MIA OH",
      "winner_seed": 11,
      "winner_elo": 1608.3,
      "loser_id": "smu",
      "loser_name": "SMU",
      "loser_seed": 11,
      "loser_elo": 1474.9,
      "winner_probability": 65.44207626661401,
      "favorite_name": "MIA OH",
      "favorite_probability": 65.44207626661401,
      "is_upset": false
    },
    {
      "round": "FirstFour",
      "round_label": "First Four",
      "region": "South",
      "slot_label": "South 16 play-in",
      "winner_id": "pvamu",
      "winner_name": "PVAMU",
      "winner_seed": 16,
      "winner_elo": 1239.7,
      "loser_id": "lehigh",
      "loser_name": "Lehigh",
      "loser_seed": 16,
      "loser_elo": 1288.2,
      "winner_probability": 46.31867228224327,
      "favorite_name": "Lehigh",
      "favorite_probability": 53.68132771775673,
      "is_upset": true
    }
  ],
  "regions": [
    {
      "name": "East",
      "rounds": {
        "R64": [
          {
            "round": "R64",
            "round_label": "Round of 64",
            "region": "East",
            "slot_label": "G1",
            "winner_id": "siena",
            "winner_name": "Siena",
            "winner_seed": 16,
            "winner_elo": 1409.9,
            "loser_id": "duke",
            "loser_name": "Duke",
            "loser_seed": 1,
            "loser_elo": 1909.7,
            "winner_probability": 7.456234890672198,
            "favorite_name": "Duke",
            "favorite_probability": 92.54376510932781,
            "is_upset": true
          },
          {
            "round": "R64",
            "round_label": "Round of 64",
            "region": "East",
            "slot_label": "G2",
            "winner_id": "tcu",
            "winner_name": "TCU",
            "winner_seed": 9,
            "winner_elo": 1638.7,
            "loser_id": "ohio_state",
            "loser_name": "Ohio State",
            "loser_seed": 8,
            "loser_elo": 1634.9,
            "winner_probability": 50.636056927662544,
            "favorite_name": "TCU",
            "favorite_probability": 50.636056927662544,
            "is_upset": false
          },
          {
            "round": "R64",
            "round_label": "Round of 64",
            "region": "East",
            "slot_label": "G3",
            "winner_id": "northern_iowa",
            "winner_name": "Northern Iowa",
            "winner_seed": 12,
            "winner_elo": 1491.7,
            "loser_id": "st_johns",
            "loser_name": "St. John's",
            "loser_seed": 5,
            "loser_elo": 1805.2,
            "winner_probability": 21.40868272202535,
            "favorite_name": "St. John's",
            "favorite_probability": 78.59131727797465,
            "is_upset": true
          },
          {
            "round": "R64",
            "round_label": "Round of 64",
            "region": "East",
            "slot_label": "G4",
            "winner_id": "cal_baptist",
            "winner_name": "Cal Baptist",
            "winner_seed": 13,
            "winner_elo": 1499.1,
            "loser_id": "kansas",
            "loser_name": "Kansas",
            "loser_seed": 4,
            "loser_elo": 1686.3,
            "winner_probability": 30.581498975387888,
            "favorite_name": "Kansas",
            "favorite_probability": 69.41850102461211,
            "is_upset": true
          },
          {
            "round": "R64",
            "round_label": "Round of 64",
            "region": "East",
            "slot_label": "G5",
            "winner_id": "south_florida",
            "winner_name": "South Florida",
            "winner_seed": 11,
            "winner_elo": 1610.7,
            "loser_id": "louisville",
            "loser_name": "Louisville",
            "loser_seed": 6,
            "loser_elo": 1629.1,
            "winner_probability": 43.81472526212765,
            "favorite_name": "Louisville",
            "favorite_probability": 56.18527473787235,
            "is_upset": true
          },
          {
            "round": "R64",
            "round_label": "Round of 64",
            "region": "East",
            "slot_label": "G6",
            "winner_id": "n_dakota_st",
            "winner_name": "N Dakota St.",
            "winner_seed": 14,
            "winner_elo": 1472.9,
            "loser_id": "michigan_st",
            "loser_name": "Michigan St.",
            "loser_seed": 3,
            "loser_elo": 1705.1,
            "winner_probability": 33.57911337325602,
            "favorite_name": "Michigan St.",
            "favorite_probability": 66.42088662674398,
            "is_upset": true
          },
          {
            "round": "R64",
            "round_label": "Round of 64",
            "region": "East",
            "slot_label": "G7",
            "winner_id": "ucla",
            "winner_name": "UCLA",
            "winner_seed": 7,
            "winner_elo": 1663.4,
            "loser_id": "ucf",
            "loser_name": "UCF",
            "loser_seed": 10,
            "loser_elo": 1545.4,
            "winner_probability": 63.637642525400985,
            "favorite_name": "UCLA",
            "favorite_probability": 63.637642525400985,
            "is_upset": false
          },
          {
            "round": "R64",
            "round_label": "Round of 64",
            "region": "East",
            "slot_label": "G8",
            "winner_id": "connecticut",
            "winner_name": "Connecticut",
            "winner_seed": 2,
            "winner_elo": 1743.3,
            "loser_id": "furman",
            "loser_name": "Furman",
            "loser_seed": 15,
            "loser_elo": 1383.2,
            "winner_probability": 87.3560998384022,
            "favorite_name": "Connecticut",
            "favorite_probability": 87.3560998384022,
            "is_upset": false
          }
        ],
        "R32": [
          {
            "round": "R32",
            "round_label": "Round of 32",
            "region": "East",
            "slot_label": "G1",
            "winner_id": "siena",
            "winner_name": "Siena",
            "winner_seed": 16,
            "winner_elo": 1409.9,
            "loser_id": "tcu",
            "loser_name": "TCU",
            "loser_seed": 9,
            "loser_elo": 1638.7,
            "winner_probability": 33.572373823451834,
            "favorite_name": "TCU",
            "favorite_probability": 66.42762617654816,
            "is_upset": true
          },
          {
            "round": "R32",
            "round_label": "Round of 32",
            "region": "East",
            "slot_label": "G2",
            "winner_id": "cal_baptist",
            "winner_name": "Cal Baptist",
            "winner_seed": 13,
            "winner_elo": 1499.1,
            "loser_id": "northern_iowa",
            "loser_name": "Northern Iowa",
            "loser_seed": 12,
            "loser_elo": 1491.7,
            "winner_probability": 51.64413111053183,
            "favorite_name": "Cal Baptist",
            "favorite_probability": 51.64413111053183,
            "is_upset": false
          },
          {
            "round": "R32",
            "round_label": "Round of 32",
            "region": "East",
            "slot_label": "G3",
            "winner_id": "n_dakota_st",
            "winner_name": "N Dakota St.",
            "winner_seed": 14,
            "winner_elo": 1472.9,
            "loser_id": "south_florida",
            "loser_name": "South Florida",
            "loser_seed": 11,
            "loser_elo": 1610.7,
            "winner_probability": 40.613653834829655,
            "favorite_name": "South Florida",
            "favorite_probability": 59.386346165170345,
            "is_upset": true
          },
          {
            "round": "R32",
            "round_label": "Round of 32",
            "region": "East",
            "slot_label": "G4",
            "winner_id": "connecticut",
            "winner_name": "Connecticut",
            "winner_seed": 2,
            "winner_elo": 1743.3,
            "loser_id": "ucla",
            "loser_name": "UCLA",
            "loser_seed": 7,
            "loser_elo": 1663.4,
            "winner_probability": 70.99063888875612,
            "favorite_name": "Connecticut",
            "favorite_probability": 70.99063888875612,
            "is_upset": false
          }
        ],
        "Sweet16": [
          {
            "round": "Sweet16",
            "round_label": "Sweet 16",
            "region": "East",
            "slot_label": "G1",
            "winner_id": "siena",
            "winner_name": "Siena",
            "winner_seed": 16,
            "winner_elo": 1409.9,
            "loser_id": "cal_baptist",
            "loser_name": "Cal Baptist",
            "loser_seed": 13,
            "loser_elo": 1499.1,
            "winner_probability": 42.09551329883917,
            "favorite_name": "Cal Baptist",
            "favorite_probability": 57.90448670116083,
            "is_upset": true
          },
          {
            "round": "Sweet16",
            "round_label": "Sweet 16",
            "region": "East",
            "slot_label": "G2",
            "winner_id": "connecticut",
            "winner_name": "Connecticut",
            "winner_seed": 2,
            "winner_elo": 1743.3,
            "loser_id": "n_dakota_st",
            "loser_name": "N Dakota St.",
            "loser_seed": 14,
            "loser_elo": 1472.9,
            "winner_probability": 82.47392264802365,
            "favorite_name": "Connecticut",
            "favorite_probability": 82.47392264802365,
            "is_upset": false
          }
        ],
        "Elite8": [
          {
            "round": "Elite8",
            "round_label": "Elite 8",
            "region": "East",
            "slot_label": "G1",
            "winner_id": "siena",
            "winner_name": "Siena",
            "winner_seed": 16,
            "winner_elo": 1409.9,
            "loser_id": "connecticut",
            "loser_name": "Connecticut",
            "loser_seed": 2,
            "loser_elo": 1743.3,
            "winner_probability": 13.821489110217074,
            "favorite_name": "Connecticut",
            "favorite_probability": 86.17851088978293,
            "is_upset": true
          }
        ]
      }
    },
    {
      "name": "West",
      "rounds": {
        "R64": [
          {
            "round": "R64",
            "round_label": "Round of 64",
            "region": "West",
            "slot_label": "G1",
            "winner_id": "long_island",
            "winner_name": "Long Island",
            "winner_seed": 16,
            "winner_elo": 1341.8,
            "loser_id": "arizona",
            "loser_name": "Arizona",
            "loser_seed": 1,
            "loser_elo": 1903.9,
            "winner_probability": 6.974990742602771,
            "favorite_name": "Arizona",
            "favorite_probability": 93.02500925739723,
            "is_upset": true
          },
          {
            "round": "R64",
            "round_label": "Round of 64",
            "region": "West",
            "slot_label": "G2",
            "winner_id": "villanova",
            "winner_name": "Villanova",
            "winner_seed": 8,
            "winner_elo": 1610.3,
            "loser_id": "utah_st",
            "loser_name": "Utah St.",
            "loser_seed": 9,
            "loser_elo": 1661.9,
            "winner_probability": 43.86161716174123,
            "favorite_name": "Utah St.",
            "favorite_probability": 56.13838283825877,
            "is_upset": true
          },
          {
            "round": "R64",
            "round_label": "Round of 64",
            "region": "West",
            "slot_label": "G3",
            "winner_id": "wisconsin",
            "winner_name": "Wisconsin",
            "winner_seed": 5,
            "winner_elo": 1696.2,
            "loser_id": "high_point",
            "loser_name": "High Point",
            "loser_seed": 12,
            "loser_elo": 1574.1,
            "winner_probability": 60.72387620992438,
            "favorite_name": "Wisconsin",
            "favorite_probability": 60.72387620992438,
            "is_upset": false
          },
          {
            "round": "R64",
            "round_label": "Round of 64",
            "region": "West",
            "slot_label": "G4",
            "winner_id": "hawaii",
            "winner_name": "Hawaii",
            "winner_seed": 13,
            "winner_elo": 1447.0,
            "loser_id": "arkansas",
            "loser_name": "Arkansas",
            "loser_seed": 4,
            "loser_elo": 1758.6,
            "winner_probability": 19.641559685942987,
            "favorite_name": "Arkansas",
            "favorite_probability": 80.358440314057,
            "is_upset": true
          },
          {
            "round": "R64",
            "round_label": "Round of 64",
            "region": "West",
            "slot_label": "G5",
            "winner_id": "byu",
            "winner_name": "BYU",
            "winner_seed": 6,
            "winner_elo": 1619.4,
            "loser_id": "texas",
            "loser_name": "Texas",
            "loser_seed": 11,
            "loser_elo": 1525.6,
            "winner_probability": 63.77561401901259,
            "favorite_name": "BYU",
            "favorite_probability": 63.77561401901259,
            "is_upset": false
          },
          {
            "round": "R64",
            "round_label": "Round of 64",
            "region": "West",
            "slot_label": "G6",
            "winner_id": "gonzaga",
            "winner_name": "Gonzaga",
            "winner_seed": 3,
            "winner_elo": 1747.0,
            "loser_id": "kennesaw_st",
            "loser_name": "Kennesaw St.",
            "loser_seed": 14,
            "loser_elo": 1409.7,
            "winner_probability": 83.40114306197812,
            "favorite_name": "Gonzaga",
            "favorite_probability": 83.40114306197812,
            "is_upset": false
          },
          {
            "round": "R64",
            "round_label": "Round of 64",
            "region": "West",
            "slot_label": "G7",
            "winner_id": "missouri",
            "winner_name": "Missouri",
            "winner_seed": 10,
            "winner_elo": 1539.2,
            "loser_id": "miami_fl",
            "loser_name": "Miami (FL)",
            "loser_seed": 7,
            "loser_elo": 1616.4,
            "winner_probability": 40.839543254206156,
            "favorite_name": "Miami (FL)",
            "favorite_probability": 59.160456745793844,
            "is_upset": true
          },
          {
            "round": "R64",
            "round_label": "Round of 64",
            "region": "West",
            "slot_label": "G8",
            "winner_id": "queens_nc",
            "winner_name": "Queens (N.C.)",
            "winner_seed": 15,
            "winner_elo": 1382.1,
            "loser_id": "purdue",
            "loser_name": "Purdue",
            "loser_seed": 2,
            "loser_elo": 1767.2,
            "winner_probability": 11.956487558170215,
            "favorite_name": "Purdue",
            "favorite_probability": 88.04351244182979,
            "is_upset": true
          }
        ],
        "R32": [
          {
            "round": "R32",
            "round_label": "Round of 32",
            "region": "West",
            "slot_label": "G1",
            "winner_id": "villanova",
            "winner_name": "Villanova",
            "winner_seed": 8,
            "winner_elo": 1610.3,
            "loser_id": "long_island",
            "loser_name": "Long Island",
            "loser_seed": 16,
            "loser_elo": 1341.8,
            "winner_probability": 69.60182554208099,
            "favorite_name": "Villanova",
            "favorite_probability": 69.60182554208099,
            "is_upset": false
          },
          {
            "round": "R32",
            "round_label": "Round of 32",
            "region": "West",
            "slot_label": "G2",
            "winner_id": "hawaii",
            "winner_name": "Hawaii",
            "winner_seed": 13,
            "winner_elo": 1447.0,
            "loser_id": "wisconsin",
            "loser_name": "Wisconsin",
            "loser_seed": 5,
            "loser_elo": 1696.2,
            "winner_probability": 27.77779155856588,
            "favorite_name": "Wisconsin",
            "favorite_probability": 72.22220844143412,
            "is_upset": true
          },
          {
            "round": "R32",
            "round_label": "Round of 32",
            "region": "West",
            "slot_label": "G3",
            "winner_id": "gonzaga",
            "winner_name": "Gonzaga",
            "winner_seed": 3,
            "winner_elo": 1747.0,
            "loser_id": "byu",
            "loser_name": "BYU",
            "loser_seed": 6,
            "loser_elo": 1619.4,
            "winner_probability": 67.50089900923241,
            "favorite_name": "Gonzaga",
            "favorite_probability": 67.50089900923241,
            "is_upset": false
          },
          {
            "round": "R32",
            "round_label": "Round of 32",
            "region": "West",
            "slot_label": "G4",
            "winner_id": "queens_nc",
            "winner_name": "Queens (N.C.)",
            "winner_seed": 15,
            "winner_elo": 1382.1,
            "loser_id": "missouri",
            "loser_name": "Missouri",
            "loser_seed": 10,
            "loser_elo": 1539.2,
            "winner_probability": 38.55947163133957,
            "favorite_name": "Missouri",
            "favorite_probability": 61.44052836866043,
            "is_upset": true
          }
        ],
        "Sweet16": [
          {
            "round": "Sweet16",
            "round_label": "Sweet 16",
            "region": "West",
            "slot_label": "G1",
            "winner_id": "villanova",
            "winner_name": "Villanova",
            "winner_seed": 8,
            "winner_elo": 1610.3,
            "loser_id": "hawaii",
            "loser_name": "Hawaii",
            "loser_seed": 13,
            "loser_elo": 1447.0,
            "winner_probability": 62.3746647509642,
            "favorite_name": "Villanova",
            "favorite_probability": 62.3746647509642,
            "is_upset": false
          },
          {
            "round": "Sweet16",
            "round_label": "Sweet 16",
            "region": "West",
            "slot_label": "G2",
            "winner_id": "queens_nc",
            "winner_name": "Queens (N.C.)",
            "winner_seed": 15,
            "winner_elo": 1382.1,
            "loser_id": "gonzaga",
            "loser_name": "Gonzaga",
            "loser_seed": 3,
            "loser_elo": 1747.0,
            "winner_probability": 15.458294608926126,
            "favorite_name": "Gonzaga",
            "favorite_probability": 84.54170539107388,
            "is_upset": true
          }
        ],
        "Elite8": [
          {
            "round": "Elite8",
            "round_label": "Elite 8",
            "region": "West",
            "slot_label": "G1",
            "winner_id": "queens_nc",
            "winner_name": "Queens (N.C.)",
            "winner_seed": 15,
            "winner_elo": 1382.1,
            "loser_id": "villanova",
            "loser_name": "Villanova",
            "loser_seed": 8,
            "loser_elo": 1610.3,
            "winner_probability": 31.630912501988206,
            "favorite_name": "Villanova",
            "favorite_probability": 68.3690874980118,
            "is_upset": true
          }
        ]
      }
    },
    {
      "name": "South",
      "rounds": {
        "R64": [
          {
            "round": "R64",
            "round_label": "Round of 64",
            "region": "South",
            "slot_label": "G1",
            "winner_id": "pvamu",
            "winner_name": "PVAMU",
            "winner_seed": 16,
            "winner_elo": 1239.7,
            "loser_id": "florida",
            "loser_name": "Florida",
            "loser_seed": 1,
            "loser_elo": 1786.4,
            "winner_probability": 7.102197695951262,
            "favorite_name": "Florida",
            "favorite_probability": 92.89780230404874,
            "is_upset": true
          },
          {
            "round": "R64",
            "round_label": "Round of 64",
            "region": "South",
            "slot_label": "G2",
            "winner_id": "iowa",
            "winner_name": "Iowa",
            "winner_seed": 9,
            "winner_elo": 1549.6,
            "loser_id": "clemson",
            "loser_name": "Clemson",
            "loser_seed": 8,
            "loser_elo": 1614.9,
            "winner_probability": 43.461973048996896,
            "favorite_name": "Clemson",
            "favorite_probability": 56.538026951003104,
            "is_upset": true
          },
          {
            "round": "R64",
            "round_label": "Round of 64",
            "region": "South",
            "slot_label": "G3",
            "winner_id": "mcneese",
            "winner_name": "McNeese",
            "winner_seed": 12,
            "winner_elo": 1583.5,
            "loser_id": "vanderbilt",
            "loser_name": "Vanderbilt",
            "loser_seed": 5,
            "loser_elo": 1686.1,
            "winner_probability": 37.50305642578417,
            "favorite_name": "Vanderbilt",
            "favorite_probability": 62.49694357421583,
            "is_upset": true
          },
          {
            "round": "R64",
            "round_label": "Round of 64",
            "region": "South",
            "slot_label": "G4",
            "winner_id": "nebraska",
            "winner_name": "Nebraska",
            "winner_seed": 4,
            "winner_elo": 1650.1,
            "loser_id": "troy",
            "loser_name": "Troy",
            "loser_seed": 13,
            "loser_elo": 1434.8,
            "winner_probability": 73.32812076016623,
            "favorite_name": "Nebraska",
            "favorite_probability": 73.32812076016623,
            "is_upset": false
          },
          {
            "round": "R64",
            "round_label": "Round of 64",
            "region": "South",
            "slot_label": "G5",
            "winner_id": "north_carolina",
            "winner_name": "North Carolina",
            "winner_seed": 6,
            "winner_elo": 1649.4,
            "loser_id": "vcu",
            "loser_name": "VCU",
            "loser_seed": 11,
            "loser_elo": 1682.5,
            "winner_probability": 49.07780557338856,
            "favorite_name": "VCU",
            "favorite_probability": 50.92219442661143,
            "is_upset": true
          },
          {
            "round": "R64",
            "round_label": "Round of 64",
            "region": "South",
            "slot_label": "G6",
            "winner_id": "penn",
            "winner_name": "Penn",
            "winner_seed": 14,
            "winner_elo": 1444.0,
            "loser_id": "illinois",
            "loser_name": "Illinois",
            "loser_seed": 3,
            "loser_elo": 1673.8,
            "winner_probability": 22.420739234235064,
            "favorite_name": "Illinois",
            "favorite_probability": 77.57926076576493,
            "is_upset": true
          },
          {
            "round": "R64",
            "round_label": "Round of 64",
            "region": "South",
            "slot_label": "G7",
            "winner_id": "saint_marys",
            "winner_name": "Saint Mary's",
            "winner_seed": 7,
            "winner_elo": 1675.7,
            "loser_id": "texas_a_and_m",
            "loser_name": "Texas A&M",
            "loser_seed": 10,
            "loser_elo": 1555.7,
            "winner_probability": 62.287074056820266,
            "favorite_name": "Saint Mary's",
            "favorite_probability": 62.287074056820266,
            "is_upset": false
          },
          {
            "round": "R64",
            "round_label": "Round of 64",
            "region": "South",
            "slot_label": "G8",
            "winner_id": "houston",
            "winner_name": "Houston",
            "winner_seed": 2,
            "winner_elo": 1777.4,
            "loser_id": "idaho",
            "loser_name": "Idaho",
            "loser_seed": 15,
            "loser_elo": 1324.6,
            "winner_probability": 90.73819981096489,
            "favorite_name": "Houston",
            "favorite_probability": 90.73819981096489,
            "is_upset": false
          }
        ],
        "R32": [
          {
            "round": "R32",
            "round_label": "Round of 32",
            "region": "South",
            "slot_label": "G1",
            "winner_id": "iowa",
            "winner_name": "Iowa",
            "winner_seed": 9,
            "winner_elo": 1549.6,
            "loser_id": "pvamu",
            "loser_name": "PVAMU",
            "loser_seed": 16,
            "loser_elo": 1239.7,
            "winner_probability": 73.3287062832781,
            "favorite_name": "Iowa",
            "favorite_probability": 73.3287062832781,
            "is_upset": false
          },
          {
            "round": "R32",
            "round_label": "Round of 32",
            "region": "South",
            "slot_label": "G2",
            "winner_id": "mcneese",
            "winner_name": "McNeese",
            "winner_seed": 12,
            "winner_elo": 1583.5,
            "loser_id": "nebraska",
            "loser_name": "Nebraska",
            "loser_seed": 4,
            "loser_elo": 1650.1,
            "winner_probability": 39.52875500400838,
            "favorite_name": "Nebraska",
            "favorite_probability": 60.47124499599161,
            "is_upset": true
          },
          {
            "round": "R32",
            "round_label": "Round of 32",
            "region": "South",
            "slot_label": "G3",
            "winner_id": "north_carolina",
            "winner_name": "North Carolina",
            "winner_seed": 6,
            "winner_elo": 1649.4,
            "loser_id": "penn",
            "loser_name": "Penn",
            "loser_seed": 14,
            "loser_elo": 1444.0,
            "winner_probability": 70.98169557756384,
            "favorite_name": "North Carolina",
            "favorite_probability": 70.98169557756384,
            "is_upset": false
          },
          {
            "round": "R32",
            "round_label": "Round of 32",
            "region": "South",
            "slot_label": "G4",
            "winner_id": "saint_marys",
            "winner_name": "Saint Mary's",
            "winner_seed": 7,
            "winner_elo": 1675.7,
            "loser_id": "houston",
            "loser_name": "Houston",
            "loser_seed": 2,
            "loser_elo": 1777.4,
            "winner_probability": 25.5811287900415,
            "favorite_name": "Houston",
            "favorite_probability": 74.4188712099585,
            "is_upset": true
          }
        ],
        "Sweet16": [
          {
            "round": "Sweet16",
            "round_label": "Sweet 16",
            "region": "South",
            "slot_label": "G1",
            "winner_id": "mcneese",
            "winner_name": "McNeese",
            "winner_seed": 12,
            "winner_elo": 1583.5,
            "loser_id": "iowa",
            "loser_name": "Iowa",
            "loser_seed": 9,
            "loser_elo": 1549.6,
            "winner_probability": 56.17374693980941,
            "favorite_name": "McNeese",
            "favorite_probability": 56.17374693980941,
            "is_upset": false
          },
          {
            "round": "Sweet16",
            "round_label": "Sweet 16",
            "region": "South",
            "slot_label": "G2",
            "winner_id": "north_carolina",
            "winner_name": "North Carolina",
            "winner_seed": 6,
            "winner_elo": 1649.4,
            "loser_id": "saint_marys",
            "loser_name": "Saint Mary's",
            "loser_seed": 7,
            "loser_elo": 1675.7,
            "winner_probability": 49.466444232831584,
            "favorite_name": "Saint Mary's",
            "favorite_probability": 50.533555767168416,
            "is_upset": true
          }
        ],
        "Elite8": [
          {
            "round": "Elite8",
            "round_label": "Elite 8",
            "region": "South",
            "slot_label": "G1",
            "winner_id": "mcneese",
            "winner_name": "McNeese",
            "winner_seed": 12,
            "winner_elo": 1583.5,
            "loser_id": "north_carolina",
            "loser_name": "North Carolina",
            "loser_seed": 6,
            "loser_elo": 1649.4,
            "winner_probability": 43.83981893728056,
            "favorite_name": "North Carolina",
            "favorite_probability": 56.16018106271944,
            "is_upset": true
          }
        ]
      }
    },
    {
      "name": "Midwest",
      "rounds": {
        "R64": [
          {
            "round": "R64",
            "round_label": "Round of 64",
            "region": "Midwest",
            "slot_label": "G1",
            "winner_id": "michigan",
            "winner_name": "Michigan",
            "winner_seed": 1,
            "winner_elo": 1872.1,
            "loser_id": "howard",
            "loser_name": "Howard",
            "loser_seed": 16,
            "loser_elo": 1351.4,
            "winner_probability": 92.29160354675604,
            "favorite_name": "Michigan",
            "favorite_probability": 92.29160354675604,
            "is_upset": false
          },
          {
            "round": "R64",
            "round_label": "Round of 64",
            "region": "Midwest",
            "slot_label": "G2",
            "winner_id": "georgia",
            "winner_name": "Georgia",
            "winner_seed": 8,
            "winner_elo": 1572.0,
            "loser_id": "saint_louis",
            "loser_name": "Saint Louis",
            "loser_seed": 9,
            "loser_elo": 1574.5,
            "winner_probability": 46.579531320702266,
            "favorite_name": "Saint Louis",
            "favorite_probability": 53.42046867929773,
            "is_upset": true
          },
          {
            "round": "R64",
            "round_label": "Round of 64",
            "region": "Midwest",
            "slot_label": "G3",
            "winner_id": "texas_tech",
            "winner_name": "Texas Tech",
            "winner_seed": 5,
            "winner_elo": 1659.7,
            "loser_id": "akron",
            "loser_name": "Akron",
            "loser_seed": 12,
            "loser_elo": 1624.2,
            "winner_probability": 56.78988135006742,
            "favorite_name": "Texas Tech",
            "favorite_probability": 56.78988135006742,
            "is_upset": false
          },
          {
            "round": "R64",
            "round_label": "Round of 64",
            "region": "Midwest",
            "slot_label": "G4",
            "winner_id": "alabama",
            "winner_name": "Alabama",
            "winner_seed": 4,
            "winner_elo": 1677.9,
            "loser_id": "hofstra",
            "loser_name": "Hofstra",
            "loser_seed": 13,
            "loser_elo": 1491.4,
            "winner_probability": 70.24819749893759,
            "favorite_name": "Alabama",
            "favorite_probability": 70.24819749893759,
            "is_upset": false
          },
          {
            "round": "R64",
            "round_label": "Round of 64",
            "region": "Midwest",
            "slot_label": "G5",
            "winner_id": "tennessee",
            "winner_name": "Tennessee",
            "winner_seed": 6,
            "winner_elo": 1612.5,
            "loser_id": "mia_oh",
            "loser_name": "MIA OH",
            "loser_seed": 11,
            "loser_elo": 1608.3,
            "winner_probability": 49.02747115332395,
            "favorite_name": "MIA OH",
            "favorite_probability": 50.97252884667605,
            "is_upset": true
          },
          {
            "round": "R64",
            "round_label": "Round of 64",
            "region": "Midwest",
            "slot_label": "G6",
            "winner_id": "virginia",
            "winner_name": "Virginia",
            "winner_seed": 3,
            "winner_elo": 1761.6,
            "loser_id": "wright_st",
            "loser_name": "Wright St.",
            "loser_seed": 14,
            "loser_elo": 1443.3,
            "winner_probability": 81.83477870008392,
            "favorite_name": "Virginia",
            "favorite_probability": 81.83477870008392,
            "is_upset": false
          },
          {
            "round": "R64",
            "round_label": "Round of 64",
            "region": "Midwest",
            "slot_label": "G7",
            "winner_id": "kentucky",
            "winner_name": "Kentucky",
            "winner_seed": 7,
            "winner_elo": 1612.7,
            "loser_id": "santa_clara",
            "loser_name": "Santa Clara",
            "loser_seed": 10,
            "loser_elo": 1616.3,
            "winner_probability": 51.440024207214876,
            "favorite_name": "Kentucky",
            "favorite_probability": 51.440024207214876,
            "is_upset": false
          },
          {
            "round": "R64",
            "round_label": "Round of 64",
            "region": "Midwest",
            "slot_label": "G8",
            "winner_id": "tennessee_st",
            "winner_name": "Tennessee St.",
            "winner_seed": 15,
            "winner_elo": 1403.2,
            "loser_id": "iowa_st",
            "loser_name": "Iowa St.",
            "loser_seed": 2,
            "loser_elo": 1719.0,
            "winner_probability": 25.508949118771017,
            "favorite_name": "Iowa St.",
            "favorite_probability": 74.49105088122899,
            "is_upset": true
          }
        ],
        "R32": [
          {
            "round": "R32",
            "round_label": "Round of 32",
            "region": "Midwest",
            "slot_label": "G1",
            "winner_id": "michigan",
            "winner_name": "Michigan",
            "winner_seed": 1,
            "winner_elo": 1872.1,
            "loser_id": "georgia",
            "loser_name": "Georgia",
            "loser_seed": 8,
            "loser_elo": 1572.0,
            "winner_probability": 86.32073017242168,
            "favorite_name": "Michigan",
            "favorite_probability": 86.32073017242168,
            "is_upset": false
          },
          {
            "round": "R32",
            "round_label": "Round of 32",
            "region": "Midwest",
            "slot_label": "G2",
            "winner_id": "texas_tech",
            "winner_name": "Texas Tech",
            "winner_seed": 5,
            "winner_elo": 1659.7,
            "loser_id": "alabama",
            "loser_name": "Alabama",
            "loser_seed": 4,
            "loser_elo": 1677.9,
            "winner_probability": 48.229949166579395,
            "favorite_name": "Alabama",
            "favorite_probability": 51.77005083342061,
            "is_upset": true
          },
          {
            "round": "R32",
            "round_label": "Round of 32",
            "region": "Midwest",
            "slot_label": "G3",
            "winner_id": "virginia",
            "winner_name": "Virginia",
            "winner_seed": 3,
            "winner_elo": 1761.6,
            "loser_id": "tennessee",
            "loser_name": "Tennessee",
            "loser_seed": 6,
            "loser_elo": 1612.5,
            "winner_probability": 70.28689272781531,
            "favorite_name": "Virginia",
            "favorite_probability": 70.28689272781531,
            "is_upset": false
          },
          {
            "round": "R32",
            "round_label": "Round of 32",
            "region": "Midwest",
            "slot_label": "G4",
            "winner_id": "kentucky",
            "winner_name": "Kentucky",
            "winner_seed": 7,
            "winner_elo": 1612.7,
            "loser_id": "tennessee_st",
            "loser_name": "Tennessee St.",
            "loser_seed": 15,
            "loser_elo": 1403.2,
            "winner_probability": 68.65243444127962,
            "favorite_name": "Kentucky",
            "favorite_probability": 68.65243444127962,
            "is_upset": false
          }
        ],
        "Sweet16": [
          {
            "round": "Sweet16",
            "round_label": "Sweet 16",
            "region": "Midwest",
            "slot_label": "G1",
            "winner_id": "texas_tech",
            "winner_name": "Texas Tech",
            "winner_seed": 5,
            "winner_elo": 1659.7,
            "loser_id": "michigan",
            "loser_name": "Michigan",
            "loser_seed": 1,
            "loser_elo": 1872.1,
            "winner_probability": 22.01744631115342,
            "favorite_name": "Michigan",
            "favorite_probability": 77.98255368884658,
            "is_upset": true
          },
          {
            "round": "Sweet16",
            "round_label": "Sweet 16",
            "region": "Midwest",
            "slot_label": "G2",
            "winner_id": "virginia",
            "winner_name": "Virginia",
            "winner_seed": 3,
            "winner_elo": 1761.6,
            "loser_id": "kentucky",
            "loser_name": "Kentucky",
            "loser_seed": 7,
            "loser_elo": 1612.7,
            "winner_probability": 69.9481948766223,
            "favorite_name": "Virginia",
            "favorite_probability": 69.9481948766223,
            "is_upset": false
          }
        ],
        "Elite8": [
          {
            "round": "Elite8",
            "round_label": "Elite 8",
            "region": "Midwest",
            "slot_label": "G1",
            "winner_id": "texas_tech",
            "winner_name": "Texas Tech",
            "winner_seed": 5,
            "winner_elo": 1659.7,
            "loser_id": "virginia",
            "loser_name": "Virginia",
            "loser_seed": 3,
            "loser_elo": 1761.6,
            "winner_probability": 36.660761031968676,
            "favorite_name": "Virginia",
            "favorite_probability": 63.33923896803133,
            "is_upset": true
          }
        ]
      }
    }
  ],
  "final_four": [
    {
      "round": "Final4",
      "round_label": "Final Four",
      "region": "Final Four",
      "slot_label": "East vs South",
      "winner_id": "siena",
      "winner_name": "Siena",
      "winner_seed": 16,
      "winner_elo": 1409.9,
      "loser_id": "mcneese",
      "loser_name": "McNeese",
      "loser_seed": 12,
      "loser_elo": 1583.5,
      "winner_probability": 34.482226480902504,
      "favorite_name": "McNeese",
      "favorite_probability": 65.51777351909749,
      "is_upset": true
    },
    {
      "round": "Final4",
      "round_label": "Final Four",
      "region": "Final Four",
      "slot_label": "Midwest vs West",
      "winner_id": "texas_tech",
      "winner_name": "Texas Tech",
      "winner_seed": 5,
      "winner_elo": 1659.7,
      "loser_id": "queens_nc",
      "loser_name": "Queens (N.C.)",
      "loser_seed": 15,
      "loser_elo": 1382.1,
      "winner_probability": 76.66987110991353,
      "favorite_name": "Texas Tech",
      "favorite_probability": 76.66987110991353,
      "is_upset": false
    }
  ],
  "championship": {
    "round": "Championship",
    "round_label": "Championship",
    "region": "Championship",
    "slot_label": "Indianapolis",
    "winner_id": "texas_tech",
    "winner_name": "Texas Tech",
    "winner_seed": 5,
    "winner_elo": 1659.7,
    "loser_id": "siena",
    "loser_name": "Siena",
    "loser_seed": 16,
    "loser_elo": 1409.9,
    "winner_probability": 74.30070796135585,
    "favorite_name": "Texas Tech",
    "favorite_probability": 74.30070796135585,
    "is_upset": false
  },
  "wildest_games": [
    {
      "round": "R64",
      "round_label": "Round of 64",
      "region": "West",
      "slot_label": "G1",
      "winner_id": "long_island",
      "winner_name": "Long Island",
      "winner_seed": 16,
      "winner_elo": 1341.8,
      "loser_id": "arizona",
      "loser_name": "Arizona",
      "loser_seed": 1,
      "loser_elo": 1903.9,
      "winner_probability": 6.974990742602771,
      "favorite_name": "Arizona",
      "favorite_probability": 93.02500925739723,
      "is_upset": true
    },
    {
      "round": "R64",
      "round_label": "Round of 64",
      "region": "South",
      "slot_label": "G1",
      "winner_id": "pvamu",
      "winner_name": "PVAMU",
      "winner_seed": 16,
      "winner_elo": 1239.7,
      "loser_id": "florida",
      "loser_name": "Florida",
      "loser_seed": 1,
      "loser_elo": 1786.4,
      "winner_probability": 7.102197695951262,
      "favorite_name": "Florida",
      "favorite_probability": 92.89780230404874,
      "is_upset": true
    },
    {
      "round": "R64",
      "round_label": "Round of 64",
      "region": "East",
      "slot_label": "G1",
      "winner_id": "siena",
      "winner_name": "Siena",
      "winner_seed": 16,
      "winner_elo": 1409.9,
      "loser_id": "duke",
      "loser_name": "Duke",
      "loser_seed": 1,
      "loser_elo": 1909.7,
      "winner_probability": 7.456234890672198,
      "favorite_name": "Duke",
      "favorite_probability": 92.54376510932781,
      "is_upset": true
    },
    {
      "round": "R64",
      "round_label": "Round of 64",
      "region": "West",
      "slot_label": "G8",
      "winner_id": "queens_nc",
      "winner_name": "Queens (N.C.)",
      "winner_seed": 15,
      "winner_elo": 1382.1,
      "loser_id": "purdue",
      "loser_name": "Purdue",
      "loser_seed": 2,
      "loser_elo": 1767.2,
      "winner_probability": 11.956487558170215,
      "favorite_name": "Purdue",
      "favorite_probability": 88.04351244182979,
      "is_upset": true
    },
    {
      "round": "Elite8",
      "round_label": "Elite 8",
      "region": "East",
      "slot_label": "G1",
      "winner_id": "siena",
      "winner_name": "Siena",
      "winner_seed": 16,
      "winner_elo": 1409.9,
      "loser_id": "connecticut",
      "loser_name": "Connecticut",
      "loser_seed": 2,
      "loser_elo": 1743.3,
      "winner_probability": 13.821489110217074,
      "favorite_name": "Connecticut",
      "favorite_probability": 86.17851088978293,
      "is_upset": true
    },
    {
      "round": "Sweet16",
      "round_label": "Sweet 16",
      "region": "West",
      "slot_label": "G2",
      "winner_id": "queens_nc",
      "winner_name": "Queens (N.C.)",
      "winner_seed": 15,
      "winner_elo": 1382.1,
      "loser_id": "gonzaga",
      "loser_name": "Gonzaga",
      "loser_seed": 3,
      "loser_elo": 1747.0,
      "winner_probability": 15.458294608926126,
      "favorite_name": "Gonzaga",
      "favorite_probability": 84.54170539107388,
      "is_upset": true
    }
  ],
  "upset_count": 35,
  "deep_upset_count": 18,
  "sample_occurrence_count": 1,
  "sample_occurrence_pct": 0.001,
  "unique_bracket_count": 100000,
  "season": 2026,
  "simulation_count": 100000,
  "seed": 42,
  "host_city": "Indianapolis",
  "final_four_pairings": [
    [
      "East",
      "South"
    ],
    [
      "Midwest",
      "West"
    ]
  ],
  "champion_name": "Texas Tech",
  "champion_seed": 5,
  "odds_label": "1 in 10^23.8"
}